{
	"deployments": {
		"testnet": {
			"freshmint-lock-box-testnet": [
				"FreshmintLockBox"
			],
			"freshmint-claim-sale-testnet": [
				"FreshmintClaimSale"
			],
			"freshmint-claim-sale-v2-testnet": [
				"FreshmintClaimSaleV2"
			],
			"freshmint-metadata-views-testnet": [
				"FreshmintMetadataViews"
			],
			"freshmint-queue-testnet": [
				"FreshmintQueue"
			],
			"freshmint-encoding-testnet": [
				"FreshmintEncoding"
			]
		}
	},
	"accounts": {
		"freshmint-lock-box-testnet": {
			"fromFile": "freshmint-testnet.private.json"
		},
		"freshmint-claim-sale-testnet": {
			"fromFile": "freshmint-testnet.private.json"
		},
		"freshmint-claim-sale-v2-testnet": {
			"fromFile": "freshmint-testnet.private.json"
		},
		"freshmint-metadata-views-testnet": {
			"fromFile": "freshmint-testnet.private.json"
		},
		"freshmint-queue-testnet": {
			"fromFile": "freshmint-testnet.private.json"
		},
		"freshmint-encoding-testnet": {
			"fromFile": "freshmint-testnet.private.json"
		}
	}
}
